flux_local/__init__.py
flux_local/command.py
flux_local/config.py
flux_local/context.py
flux_local/exceptions.py
flux_local/git_repo.py
flux_local/helm.py
flux_local/image.py
flux_local/kustomize.py
flux_local/manifest.py
flux_local/resource_diff.py
flux_local/values.py
flux_local/visitor.py
flux_local/helm_controller/__init__.py
flux_local/helm_controller/artifact.py
flux_local/helm_controller/controller.py
flux_local/kustomize_controller/__init__.py
flux_local/kustomize_controller/artifact.py
flux_local/kustomize_controller/controller.py
flux_local/orchestrator/__init__.py
flux_local/orchestrator/loader.py
flux_local/orchestrator/orchestrator.py
flux_local/source_controller/__init__.py
flux_local/source_controller/artifact.py
flux_local/source_controller/cache.py
flux_local/source_controller/controller.py
flux_local/source_controller/git.py
flux_local/source_controller/oci.py
flux_local/source_controller/secret.py
flux_local/store/__init__.py
flux_local/store/artifact.py
flux_local/store/in_memory.py
flux_local/store/status.py
flux_local/store/store.py
flux_local/store/watcher.py
flux_local/task/__init__.py
flux_local/task/context.py
flux_local/task/service.py
flux_local/tool/__init__.py
flux_local/tool/build.py
flux_local/tool/build_common.py
flux_local/tool/build_helm.py
flux_local/tool/build_kustomization.py
flux_local/tool/diagnostics.py
flux_local/tool/diff.py
flux_local/tool/flux_local.py
flux_local/tool/format.py
flux_local/tool/get.py
flux_local/tool/get_common.py
flux_local/tool/get_helm.py
flux_local/tool/get_kustomization.py
flux_local/tool/selector.py
flux_local/tool/test.py
flux_local/tool/shell/__init__.py
flux_local/tool/shell/action.py
flux_local/tool/shell/repl.py
flux_local-8.1.0.dist-info/licenses/LICENSE
flux_local-8.1.0.dist-info/METADATA
flux_local-8.1.0.dist-info/WHEEL
flux_local-8.1.0.dist-info/entry_points.txt
flux_local-8.1.0.dist-info/top_level.txt
flux_local-8.1.0.dist-info/RECORD
