Metadata-Version: 2.4
Name: flux_local
Version: 8.1.0
Summary: flux-local is a set of tools and libraries for managing a local flux gitops repository focused on validation steps to help improve quality of commits, PRs, and general local testing.
Author-email: Allen Porter <allen.porter@gmail.com>
License-Expression: Apache-2.0
Project-URL: Source, https://github.com/allenporter/flux_local
Requires-Python: >=3.13
License-File: LICENSE
Requires-Dist: GitPython>=3.1.30
Requires-Dist: PyYAML>=6.0
Requires-Dist: aiofiles>=22.1.0
Requires-Dist: mashumaro>=3.12
Requires-Dist: nest-asyncio>=1.5.6
Requires-Dist: oras>=0.2.31
Requires-Dist: pytest>=7.2.1
Requires-Dist: pytest-asyncio>=0.20.3
Requires-Dist: python-slugify>=8.0.1
Dynamic: license-file
